[
  {
    "_id": "6759b00f1234567890abcdef",
    "conejo": {
      "_id": "6759b00f1234567890abcde1",
      "codigo": "CNJ001",
      "nombre": "Conejo Alpha",
      "sexo": "hembra",
      "proposito": "reproducción"
    },
    "jaula": {
      "_id": "6759b00f1234567890abcde5",
      "numero": "001",
      "tipo": "reproducción",
      "ubicacion": "Galpón A - Sección 1"
    },
    "fechaAsignacion": "2023-10-15T00:00:00.000Z",
    "estado": "activa",
    "motivo": "Asignación inicial para reproducción",
    "asignadoPor": "admin",
    "historialTransferencias": [],
    "createdAt": "2023-10-15T00:00:00.000Z",
    "updatedAt": "2023-10-15T00:00:00.000Z"
  },
  {
    "_id": "6759b00f1234567890abcdf0",
    "conejo": {
      "_id": "6759b00f1234567890abcde2",
      "codigo": "CNJ002",
      "nombre": "Conejo Beta",
      "sexo": "macho",
      "proposito": "reproducción"
    },
    "jaula": {
      "_id": "6759b00f1234567890abcde6",
      "numero": "002",
      "tipo": "reproducción",
      "ubicacion": "Galpón A - Sección 2"
    },
    "fechaAsignacion": "2023-09-20T00:00:00.000Z",
    "estado": "activa",
    "motivo": "Semental principal",
    "asignadoPor": "admin",
    "historialTransferencias": [],
    "createdAt": "2023-09-20T00:00:00.000Z",
    "updatedAt": "2023-09-20T00:00:00.000Z"
  },
  {
    "_id": "6759b00f1234567890abcdf1",
    "conejo": {
      "_id": "6759b00f1234567890abcde3",
      "codigo": "CNJ003",
      "nombre": "Conejo Gamma",
      "sexo": "hembra",
      "proposito": "engorde"
    },
    "jaula": {
      "_id": "6759b00f1234567890abcde7",
      "numero": "003",
      "tipo": "engorde",
      "ubicacion": "Galpón B - Sección 1"
    },
    "fechaAsignacion": "2023-12-01T00:00:00.000Z",
    "estado": "activa",
    "motivo": "Engorde grupal",
    "asignadoPor": "admin",
    "historialTransferencias": [],
    "createdAt": "2023-12-01T00:00:00.000Z",
    "updatedAt": "2023-12-01T00:00:00.000Z"
  },
  {
    "_id": "6759b00f1234567890abcdf2",
    "conejo": {
      "_id": "6759b00f1234567890abcde4",
      "codigo": "CNJ004",
      "nombre": "Conejo Delta",
      "sexo": "macho",
      "proposito": "engorde"
    },
    "jaula": {
      "_id": "6759b00f1234567890abcde7",
      "numero": "003",
      "tipo": "engorde",
      "ubicacion": "Galpón B - Sección 1"
    },
    "fechaAsignacion": "2023-11-10T00:00:00.000Z",
    "estado": "activa",
    "motivo": "Engorde grupal con hermano",
    "asignadoPor": "admin",
    "historialTransferencias": [
      {
        "fecha": "2023-11-15T00:00:00.000Z",
        "jaulaAnterior": "004",
        "jaulaNueva": "003",
        "motivo": "Optimización de espacio",
        "realizadoPor": "admin"
      }
    ],
    "createdAt": "2023-11-10T00:00:00.000Z",
    "updatedAt": "2023-11-15T00:00:00.000Z"
  }
]
